{"game_id":"UG4kDZLDvo","user_id":"111374135736029697427","artist":"OH MY GIRL","title":"Dun Dun Dance","difficulty":"0","video_id":"0l9LB_Noe2Q","wave_n_beat_1":"{\"wave_list\":[{\"t\":0,\"type\":\"RANDOM\",\"background_uid\":null}],\"beat_list\":[{\"t\":3170,\"m\":1},{\"t\":4153,\"m\":2},{\"t\":5202,\"m\":2},{\"t\":6253,\"m\":2},{\"t\":7303,\"m\":8},{\"t\":8319,\"m\":16},{\"t\":9403,\"m\":24},{\"t\":10436,\"m\":3},{\"t\":11535,\"m\":9},{\"t\":12504,\"m\":17},{\"t\":13569,\"m\":9},{\"t\":14585,\"m\":12},{\"t\":15685,\"m\":17},{\"t\":16751,\"m\":17},{\"t\":17769,\"m\":8},{\"t\":18818,\"m\":1},{\"t\":19835,\"m\":16},{\"t\":20902,\"m\":16}]}","wave_n_beat_2":null,"wave_n_beat_3":null,"play_count":0,"timestamp_created":"2022-02-23T12:23:19.000Z","timestamp_modified":"2022-02-25T10:31:23.000Z","game_type":4,"like_count":0,"base_offset_ms":0,"is_public":0,"particle_list":"[{\"particle_uid\":\"oC2kzrevi8\",\"image_path\":\"/upload/particle/oC2kzrevi8.png\"},{\"particle_uid\":\"oC2kzrevi8\",\"image_path\":\"/upload/particle/oC2kzrevi8.png\"},{\"particle_uid\":\"oC2kzrevi8\",\"image_path\":\"/upload/particle/oC2kzrevi8.png\"},{\"particle_uid\":\"oC2kzrevi8\",\"image_path\":\"/upload/particle/oC2kzrevi8.png\"},{\"particle_uid\":\"oC2kzrevi8\",\"image_path\":\"/upload/particle/oC2kzrevi8.png\"}]","beat_atlas_uid":"dslBBcSdHp","score_fill_color":"#000000","score_use_stroke":0,"score_stroke_color":"#000000","score_line_width":1,"hit_fill_color":"#000000","hit_use_stroke":0,"hit_stroke_color":"#000000","hit_line_width":1,"combo_fill_color":"#000000","combo_use_stroke":0,"combo_stroke_color":"#000000","combo_line_width":1,"result_fill_color":"#000000","result_use_stroke":0,"result_stroke_color":"#000000","result_line_width":1,"beat_atlas_image_path":"/upload/beat_atlas/dslBBcSdHp.png","background_list":"[{\"background_uid\":\"sDV0opAvZ8\",\"display_order\":1,\"name\":\"test\",\"layer1_color\":\"\",\"layer1_image_path\":\"/upload/background/sDV0opAvZ8_1.png\",\"layer1_action\":\"right\",\"layer1_speed\":1,\"layer2_color\":\"\",\"layer2_image_path\":\"\",\"layer2_action\":\"fixed\",\"layer2_speed\":10,\"layer3_color\":\"\",\"layer3_image_path\":\"\",\"layer3_action\":\"fixed\",\"layer3_speed\":1,\"timestamp_created\":\"2022-01-30T09:02:43.000Z\",\"timestamp_updated\":\"2022-02-15T10:37:54.000Z\"}]"}